{
  "openapi": "3.0.4",
  "info": {
    "title": "THCY_BE",
    "version": "1.0"
  },
  "paths": {
    "/api/Default": {
      "get": {
        "tags": [
          "Default"
        ],
        "responses": {
          "200": {
            "description": "OK"
          }
        }
      }
    },
    "/api/Default/health": {
      "get": {
        "tags": [
          "Default"
        ],
        "responses": {
          "200": {
            "description": "OK"
          }
        }
      }
    },
    "/api/Default/users/count": {
      "get": {
        "tags": [
          "Default"
        ],
        "responses": {
          "200": {
            "description": "OK"
          }
        }
      }
    }
  },
  "components": { }
}